{
  "project_id": "be379927-9034-4a4d-8e35-4fbdfe258fc0",
  "service_id": "bac72d7a-eeca-4dda-acd9-6b0496a2184f",
  "environment_id": "efc4bf86-aec3-4fe7-afb7-f7409837f876",
  "root_directory": "whatsapp-backend",
  "build_command": "npm install",
  "start_command": "node server.js",
  "healthcheck_path": "/health",
  "required_env_vars": [
    "GOOGLE_APPLICATION_CREDENTIALS_JSON",
    "NODE_ENV",
    "PORT"
  ],
  "notes": "Service must be configured in Railway dashboard with root directory set to whatsapp-backend"
}
